Metadata-Version: 1.0
Name: cppyad
Version: 0.1.2
Summary: Python bindings to Coin-OR CppAD
Home-page: UNKNOWN
Author: Francesco Ceccon
Author-email: francesco@ceccon.me
License: Apache 2.0
Platform: UNKNOWN
